243_22562_180-pycharm-support-libs/__init__.py
243_22562_180-pycharm-support-libs/interpreterInfo.py
243_22562_180-pycharm-support-libs/pycompletionserver.py
243_22562_180-pycharm-support-libs/pydev_app_engine_debug_startup.py
243_22562_180-pycharm-support-libs/pydev_coverage.py
243_22562_180-pycharm-support-libs/pydev_jupyter_plugin.py
243_22562_180-pycharm-support-libs/pydev_jupyter_utils.py
243_22562_180-pycharm-support-libs/pydev_jupyter_vars.py
243_22562_180-pycharm-support-libs/pydev_pysrc.py
243_22562_180-pycharm-support-libs/pydevconsole.py
243_22562_180-pycharm-support-libs/pydevd.py
243_22562_180-pycharm-support-libs/pydevd_file_utils.py
243_22562_180-pycharm-support-libs/pydevd_pycharm.py
243_22562_180-pycharm-support-libs/pydevd_tracing.py
243_22562_180-pycharm-support-libs/runfiles.py
243_22562_180-pycharm-support-libs/setup_cython.py
243_22562_180-pycharm-support-libs/_pydev_bundle/__init__.py
243_22562_180-pycharm-support-libs/_pydev_bundle/_pydev_calltip_util.py
243_22562_180-pycharm-support-libs/_pydev_bundle/_pydev_completer.py
243_22562_180-pycharm-support-libs/_pydev_bundle/_pydev_filesystem_encoding.py
243_22562_180-pycharm-support-libs/_pydev_bundle/_pydev_getopt.py
243_22562_180-pycharm-support-libs/_pydev_bundle/_pydev_imports_tipper.py
243_22562_180-pycharm-support-libs/_pydev_bundle/_pydev_jy_imports_tipper.py
243_22562_180-pycharm-support-libs/_pydev_bundle/_pydev_log.py
243_22562_180-pycharm-support-libs/_pydev_bundle/_pydev_tipper_common.py
243_22562_180-pycharm-support-libs/_pydev_bundle/fix_getpass.py
243_22562_180-pycharm-support-libs/_pydev_bundle/pydev_code_executor.py
243_22562_180-pycharm-support-libs/_pydev_bundle/pydev_console_commands.py
243_22562_180-pycharm-support-libs/_pydev_bundle/pydev_console_types.py
243_22562_180-pycharm-support-libs/_pydev_bundle/pydev_console_utils.py
243_22562_180-pycharm-support-libs/_pydev_bundle/pydev_import_hook.py
243_22562_180-pycharm-support-libs/_pydev_bundle/pydev_imports.py
phyloRNN-0.45.dist-info/LICENSE
phyloRNN-0.45.dist-info/METADATA
phyloRNN-0.45.dist-info/WHEEL
phyloRNN-0.45.dist-info/top_level.txt
phyloRNN-0.45.dist-info/RECORD
